dgeb/__init__.py
dgeb/cli.py
dgeb/dgeb.py
dgeb/eval_utils.py
dgeb/evaluators.py
dgeb/modality.py
dgeb/models.py
dgeb/tasks/__init__.py
dgeb/tasks/bigene_mining_tasks.py
dgeb/tasks/classification_tasks.py
dgeb/tasks/clustering_tasks.py
dgeb/tasks/eds_tasks.py
dgeb/tasks/pair_classification_tasks.py
dgeb/tasks/retrieval_tasks.py
dgeb/tasks/tasks.py
leaderboard/submissions/esm2_t12_35M_UR50D/MIBIG_protein_classification.json
leaderboard/submissions/esm2_t12_35M_UR50D/arch_retrieval.json
leaderboard/submissions/esm2_t12_35M_UR50D/bacarch_bigene.json
leaderboard/submissions/esm2_t12_35M_UR50D/convergent_enzymes_classification.json
leaderboard/submissions/esm2_t12_35M_UR50D/cyano_operonic_pair.json
leaderboard/submissions/esm2_t12_35M_UR50D/ec_classification.json
leaderboard/submissions/esm2_t12_35M_UR50D/ecoli_operonic_pair.json
leaderboard/submissions/esm2_t12_35M_UR50D/euk_retrieval.json
leaderboard/submissions/esm2_t12_35M_UR50D/fefe_phylogeny.json
leaderboard/submissions/esm2_t12_35M_UR50D/modac_paralogy_bigene.json
leaderboard/submissions/esm2_t12_35M_UR50D/mopb_clustering.json
leaderboard/submissions/esm2_t12_35M_UR50D/rpob_arch_phylogeny.json
leaderboard/submissions/esm2_t12_35M_UR50D/rpob_bac_phylogeny.json
leaderboard/submissions/esm2_t12_35M_UR50D/vibrio_operonic_pair.json
leaderboard/submissions/esm2_t30_150M_UR50D/MIBIG_protein_classification.json
leaderboard/submissions/esm2_t30_150M_UR50D/arch_retrieval.json
leaderboard/submissions/esm2_t30_150M_UR50D/bacarch_bigene.json
leaderboard/submissions/esm2_t30_150M_UR50D/convergent_enzymes_classification.json
leaderboard/submissions/esm2_t30_150M_UR50D/cyano_operonic_pair.json
leaderboard/submissions/esm2_t30_150M_UR50D/ec_classification.json
leaderboard/submissions/esm2_t30_150M_UR50D/ecoli_operonic_pair.json
leaderboard/submissions/esm2_t30_150M_UR50D/euk_retrieval.json
leaderboard/submissions/esm2_t30_150M_UR50D/fefe_phylogeny.json
leaderboard/submissions/esm2_t30_150M_UR50D/modac_paralogy_bigene.json
dgeb-0.2.0.dist-info/LICENSE
dgeb-0.2.0.dist-info/METADATA
dgeb-0.2.0.dist-info/WHEEL
dgeb-0.2.0.dist-info/entry_points.txt
dgeb-0.2.0.dist-info/top_level.txt
dgeb-0.2.0.dist-info/RECORD
