Metadata-Version: 2.1
Name: dgeb
Version: 0.2.0
Summary: Diverse Genomic Embedding Benchmark
License: Apache License
Project-URL: homepage, https://github.com/TattaBio/DGEB
Project-URL: Huggingface Organization, https://huggingface.co/tattabio
Project-URL: Source Code, https://github.com/TattaBio/DGEB
Keywords: scientific software,genomic embeddings,machine learning,benchmark
Classifier: Development Status :: 2 - Pre-Alpha
Classifier: Environment :: Console
Classifier: Intended Audience :: Developers
Classifier: Intended Audience :: Information Technology
Classifier: Intended Audience :: Science/Research
Classifier: License :: OSI Approved :: Apache Software License
Classifier: Operating System :: OS Independent
Classifier: Programming Language :: Python
License-File: LICENSE
Requires-Dist: datasets>=2.20.0
Requires-Dist: matplotlib>=3.9.0
Requires-Dist: numpy>=1.0.0
Requires-Dist: pandas>=2.2.2
Requires-Dist: pydantic>=2.0.0
Requires-Dist: pytrec-eval-terrier>=0.5
Requires-Dist: rich>=13.7.1
Requires-Dist: scikit-learn>=1.5.0
Requires-Dist: scipy>=1.13.1
Requires-Dist: seaborn>=0.13.2
Requires-Dist: torch>1.0.0
Requires-Dist: tqdm>=4.66.4
Requires-Dist: transformers>=4.41.2
Provides-Extra: dev
Requires-Dist: ruff>=0.0.254; extra == "dev"
Requires-Dist: pytest; extra == "dev"
Requires-Dist: pytest-xdist; extra == "dev"
